{"cameraMode":{"drawMode":0,"name":"Shaded","section":"Shading Mode"},"sceneLighting":true,"audioPlay":false,"sceneViewState":{"m_AlwaysRefresh":false,"showFog":true,"showSkybox":true,"showFlares":true,"showImageEffects":true,"showParticleSystems":true,"showVisualEffectGraphs":true,"m_FxEnabled":true},"in2DMode":false,"pivot":{"x":-0.3462529182434082,"y":1.5207247734069825,"z":-0.5231943130493164},"rotation":{"x":-0.05815090239048004,"y":0.9150826930999756,"z":-0.14280621707439423,"w":-0.37262290716171267},"size":5.720045566558838,"orthographic":false}